uniflash
