Metadata-Version: 1.0
Name: uniflash
Version: 1.1
Summary: Reflash Logitech Unifying Receivers easily
Home-page: UNKNOWN
Author: athn
Author-email: jem@seethis.link
License: MIT
Platform: UNKNOWN
